mne_realtime/__init__.py
mne_realtime/_version.py
mne_realtime/base_client.py
mne_realtime/client.py
mne_realtime/conftest.py
mne_realtime/epochs.py
mne_realtime/fieldtrip_client.py
mne_realtime/lsl_client.py
mne_realtime/mock_client.py
mne_realtime/mock_lsl_stream.py
mne_realtime/rt_filter.py
mne_realtime/stim_server_client.py
mne_realtime/externals/FieldTrip.py
mne_realtime/externals/__init__.py
mne_realtime/tests/__init__.py
mne_realtime/tests/test_base_client.py
mne_realtime/tests/test_fieldtrip_client.py
mne_realtime/tests/test_lsl_client.py
mne_realtime/tests/test_mock_client.py
mne_realtime/tests/test_stim_client_server.py
mne_realtime-0.3.0.dist-info/LICENSE.txt
mne_realtime-0.3.0.dist-info/METADATA
mne_realtime-0.3.0.dist-info/WHEEL
mne_realtime-0.3.0.dist-info/top_level.txt
mne_realtime-0.3.0.dist-info/RECORD
